wuxctools/__init__.py
wuxctools/cli.py
wuxctools/plot/__init__.py
wuxctools/plot/cli.py
wuxctools/plot/common_params.py
wuxctools/plot/simple_plots/__init__.py
wuxctools/plot/simple_plots/bar.py
wuxctools/plot/simple_plots/line.py
wuxctools/plot/simple_plots/scatter.py
wuxctools/plot/simple_plots/smiles.py
wuxctools/utils/__init__.py
wuxctools/utils/plot.py
wuxctools/vasp/__init__.py
wuxctools/vasp/cli.py
wuxctools/vasp/dataread/__init__.py
wuxctools/vasp/dataread/vaspdata.py
wuxctools/vasp/dataread/vaspout.py
wuxctools/vasp/dataread/vasprun.py
wuxctools/vasp/subcommand/__init__.py
wuxctools/vasp/subcommand/band.py
wuxctools/vasp/subcommand/bandplot.py
wuxctools/vasp/subcommand/dos.py
wuxctools/vasp/subcommand/dosplot.py
wuxctools/vasp/subcommand/parsepro.py
wuxctools/wuxc.mplstyle
wuxctools-0.1.2.dist-info/WHEEL
wuxctools-0.1.2.dist-info/entry_points.txt
wuxctools-0.1.2.dist-info/METADATA
wuxctools-0.1.2.dist-info/RECORD
