Metadata-Version: 2.3
Name: wuxctools
Version: 0.1.2
Summary: xucai's personal scripts
Requires-Dist: altair-viewer>=0.4.0
Requires-Dist: colorcet>=3.1.0
Requires-Dist: h5py>=3.15.1
Requires-Dist: holoviews>=1.22.1
Requires-Dist: lxml>=6.0.2
Requires-Dist: matplotlib>=3.10.7
Requires-Dist: msgspec>=0.20.0
Requires-Dist: numpy>=2.3.5
Requires-Dist: plotly>=6.5.0
Requires-Dist: polars[rtcompat]>=1.35.2
Requires-Dist: rdkit>=2025.9.3
Requires-Dist: rich>=14.2.0
Requires-Dist: tqdm>=4.67.1
Requires-Dist: tyro>=0.9.35
Requires-Dist: pymatgen>=2025.10.7 ; extra == 'pymatgen'
Requires-Python: >=3.13
Provides-Extra: pymatgen
